PyHook3/HookManager.py
PyHook3/__init__.py
PyHook3/_cpyHook.pyd
PyHook3/aa hook.py
PyHook3/cpyHook.py
PyHook3/doc.py
PyHook3/example.py
PyHook3-1.6.1.data/data/Lib/site-packages/PyHook3/CHANGELOG.txt
PyHook3-1.6.1.data/data/Lib/site-packages/PyHook3/LICENSE.rst
PyHook3-1.6.1.data/data/Lib/site-packages/PyHook3/README.rst
PyHook3-1.6.1.dist-info/DESCRIPTION.rst
PyHook3-1.6.1.dist-info/METADATA
PyHook3-1.6.1.dist-info/RECORD
PyHook3-1.6.1.dist-info/WHEEL
PyHook3-1.6.1.dist-info/metadata.json
PyHook3-1.6.1.dist-info/top_level.txt
